hf_mirror_hub/__init__.py
hf_mirror_hub/cli.py
hf_mirror_hub-0.0.4.dist-info/LICENSE
hf_mirror_hub-0.0.4.dist-info/METADATA
hf_mirror_hub-0.0.4.dist-info/WHEEL
hf_mirror_hub-0.0.4.dist-info/entry_points.txt
hf_mirror_hub-0.0.4.dist-info/RECORD
