Metadata-Version: 2.3
Name: hf-mirror-hub
Version: 0.0.4
Summary: A CLI tool to download Hugging Face models and datasets from mirror sites.
License: MIT
Author: neverbiasu
Author-email: 1751162157@qq.com
Requires-Python: >=3.8,<4.0
Classifier: License :: OSI Approved :: MIT License
Classifier: Programming Language :: Python :: 3
Classifier: Programming Language :: Python :: 3.8
Classifier: Programming Language :: Python :: 3.9
Classifier: Programming Language :: Python :: 3.10
Classifier: Programming Language :: Python :: 3.11
Classifier: Programming Language :: Python :: 3.12
Classifier: Programming Language :: Python :: 3.13
Requires-Dist: flake8
Requires-Dist: hf-transfer
Requires-Dist: huggingface_hub
Requires-Dist: pytest
Requires-Dist: requests
